pygsc/CharTree.py
pygsc/CommandParser.py
pygsc/MessageDisplay.py
pygsc/MonitorClient.py
pygsc/MonitorServer.py
pygsc/Script.py
pygsc/ScriptRecorder.py
pygsc/ScriptedSession.py
pygsc/TerminalSession.py
pygsc/UserInputHandler.py
pygsc/__init__.py
pygsc/cli.py
pygsc-0.7.dist-info/entry_points.txt
pygsc-0.7.dist-info/WHEEL
pygsc-0.7.dist-info/METADATA
pygsc-0.7.dist-info/RECORD
