Metadata-Version: 2.1
Name: pygsc
Version: 0.7
Summary: Run command-line demos from a script.
License: MIT
Author: CD Clark III
Author-email: clifton.clark@gmail.com
Requires-Python: >=3.10,<4.0
Classifier: License :: OSI Approved :: MIT License
Classifier: Programming Language :: Python :: 3
Classifier: Programming Language :: Python :: 3.10
Classifier: Programming Language :: Python :: 3.11
Requires-Dist: blessed
Requires-Dist: click
Requires-Dist: pygame
Requires-Dist: pyparsing
Requires-Dist: urwid
